{"nodes": [{"id": "src_preset_manager_dirs_cpp", "label": "preset_manager_dirs.cpp", "file_type": "code", "source_file": "src/preset_manager_dirs.cpp", "source_location": "L1"}, {"id": "preset_manager_dirs_append_json_files", "label": "append_json_files()", "file_type": "code", "source_file": "src/preset_manager_dirs.cpp", "source_location": "L24"}, {"id": "preset_manager_dirs_get_bundled_presets_dir", "label": "get_bundled_presets_dir()", "file_type": "code", "source_file": "src/preset_manager_dirs.cpp", "source_location": "L53"}, {"id": "preset_manager_dirs_set_presets_dir", "label": "set_presets_dir()", "file_type": "code", "source_file": "src/preset_manager_dirs.cpp", "source_location": "L86"}, {"id": "preset_manager_dirs_save_config", "label": "save_config()", "file_type": "code", "source_file": "src/preset_manager_dirs.cpp", "source_location": "L106"}, {"id": "preset_manager_dirs_load_config", "label": "load_config()", "file_type": "code", "source_file": "src/preset_manager_dirs.cpp", "source_location": "L120"}, {"id": "preset_manager_dirs_get_presets_dir", "label": "get_presets_dir()", "file_type": "code", "source_file": "src/preset_manager_dirs.cpp", "source_location": "L158"}, {"id": "preset_manager_dirs_save_factory_presets", "label": "save_factory_presets()", "file_type": "code", "source_file": "src/preset_manager_dirs.cpp", "source_location": "L183"}], "edges": [{"source": "src_preset_manager_dirs_cpp", "target": "preset_manager", "relation": "imports", "confidence": "EXTRACTED", "source_file": "src/preset_manager_dirs.cpp", "source_location": "L1", "weight": 1.0}, {"source": "src_preset_manager_dirs_cpp", "target": "preset_manager_impl", "relation": "imports", "confidence": "EXTRACTED", "source_file": "src/preset_manager_dirs.cpp", "source_location": "L2", "weight": 1.0}, {"source": "src_preset_manager_dirs_cpp", "target": "iostream", "relation": "imports", "confidence": "EXTRACTED", "source_file": "src/preset_manager_dirs.cpp", "source_location": "L3", "weight": 1.0}, {"source": "src_preset_manager_dirs_cpp", "target": "cstdlib", "relation": "imports", "confidence": "EXTRACTED", "source_file": "src/preset_manager_dirs.cpp", "source_location": "L4", "weight": 1.0}, {"source": "src_preset_manager_dirs_cpp", "target": "filesystem", "relation": "imports", "confidence": "EXTRACTED", "source_file": "src/preset_manager_dirs.cpp", "source_location": "L5", "weight": 1.0}, {"source": "src_preset_manager_dirs_cpp", "target": "stat", "relation": "imports", "confidence": "EXTRACTED", "source_file": "src/preset_manager_dirs.cpp", "source_location": "L6", "weight": 1.0}, {"source": "src_preset_manager_dirs_cpp", "target": "direct", "relation": "imports", "confidence": "EXTRACTED", "source_file": "src/preset_manager_dirs.cpp", "source_location": "L9", "weight": 1.0}, {"source": "src_preset_manager_dirs_cpp", "target": "io", "relation": "imports", "confidence": "EXTRACTED", "source_file": "src/preset_manager_dirs.cpp", "source_location": "L10", "weight": 1.0}, {"source": "src_preset_manager_dirs_cpp", "target": "windows", "relation": "imports", "confidence": "EXTRACTED", "source_file": "src/preset_manager_dirs.cpp", "source_location": "L11", "weight": 1.0}, {"source": "src_preset_manager_dirs_cpp", "target": "dirent", "relation": "imports", "confidence": "EXTRACTED", "source_file": "src/preset_manager_dirs.cpp", "source_location": "L14", "weight": 1.0}, {"source": "src_preset_manager_dirs_cpp", "target": "dyld", "relation": "imports", "confidence": "EXTRACTED", "source_file": "src/preset_manager_dirs.cpp", "source_location": "L15", "weight": 1.0}, {"source": "src_preset_manager_dirs_cpp", "target": "dirent", "relation": "imports", "confidence": "EXTRACTED", "source_file": "src/preset_manager_dirs.cpp", "source_location": "L18", "weight": 1.0}, {"source": "src_preset_manager_dirs_cpp", "target": "preset_manager_dirs_append_json_files", "relation": "contains", "confidence": "EXTRACTED", "source_file": "src/preset_manager_dirs.cpp", "source_location": "L24", "weight": 1.0}, {"source": "src_preset_manager_dirs_cpp", "target": "preset_manager_dirs_get_bundled_presets_dir", "relation": "contains", "confidence": "EXTRACTED", "source_file": "src/preset_manager_dirs.cpp", "source_location": "L53", "weight": 1.0}, {"source": "src_preset_manager_dirs_cpp", "target": "preset_manager_dirs_set_presets_dir", "relation": "contains", "confidence": "EXTRACTED", "source_file": "src/preset_manager_dirs.cpp", "source_location": "L86", "weight": 1.0}, {"source": "src_preset_manager_dirs_cpp", "target": "preset_manager_dirs_save_config", "relation": "contains", "confidence": "EXTRACTED", "source_file": "src/preset_manager_dirs.cpp", "source_location": "L106", "weight": 1.0}, {"source": "src_preset_manager_dirs_cpp", "target": "preset_manager_dirs_load_config", "relation": "contains", "confidence": "EXTRACTED", "source_file": "src/preset_manager_dirs.cpp", "source_location": "L120", "weight": 1.0}, {"source": "src_preset_manager_dirs_cpp", "target": "preset_manager_dirs_get_presets_dir", "relation": "contains", "confidence": "EXTRACTED", "source_file": "src/preset_manager_dirs.cpp", "source_location": "L158", "weight": 1.0}, {"source": "src_preset_manager_dirs_cpp", "target": "preset_manager_dirs_save_factory_presets", "relation": "contains", "confidence": "EXTRACTED", "source_file": "src/preset_manager_dirs.cpp", "source_location": "L183", "weight": 1.0}, {"source": "preset_manager_dirs_set_presets_dir", "target": "preset_manager_dirs_append_json_files", "relation": "calls", "confidence": "EXTRACTED", "source_file": "src/preset_manager_dirs.cpp", "source_location": "L99", "weight": 1.0}, {"source": "preset_manager_dirs_set_presets_dir", "target": "preset_manager_dirs_save_factory_presets", "relation": "calls", "confidence": "EXTRACTED", "source_file": "src/preset_manager_dirs.cpp", "source_location": "L101", "weight": 1.0}, {"source": "preset_manager_dirs_save_factory_presets", "target": "preset_manager_dirs_get_bundled_presets_dir", "relation": "calls", "confidence": "EXTRACTED", "source_file": "src/preset_manager_dirs.cpp", "source_location": "L184", "weight": 1.0}, {"source": "preset_manager_dirs_save_factory_presets", "target": "preset_manager_dirs_append_json_files", "relation": "calls", "confidence": "EXTRACTED", "source_file": "src/preset_manager_dirs.cpp", "source_location": "L191", "weight": 1.0}]}