{"nodes": [{"id": "src_gui_gui_manager_frame_cpp", "label": "gui_manager_frame.cpp", "file_type": "code", "source_file": "src/gui/gui_manager_frame.cpp", "source_location": "L1"}, {"id": "gui_manager_frame_run_frame", "label": "run_frame()", "file_type": "code", "source_file": "src/gui/gui_manager_frame.cpp", "source_location": "L12"}, {"id": "gui_manager_frame_render_master_controls", "label": "render_master_controls()", "file_type": "code", "source_file": "src/gui/gui_manager_frame.cpp", "source_location": "L137"}], "edges": [{"source": "src_gui_gui_manager_frame_cpp", "target": "gui_manager", "relation": "imports", "confidence": "EXTRACTED", "source_file": "src/gui/gui_manager_frame.cpp", "source_location": "L1", "weight": 1.0}, {"source": "src_gui_gui_manager_frame_cpp", "target": "pedal_board", "relation": "imports", "confidence": "EXTRACTED", "source_file": "src/gui/gui_manager_frame.cpp", "source_location": "L2", "weight": 1.0}, {"source": "src_gui_gui_manager_frame_cpp", "target": "theme", "relation": "imports", "confidence": "EXTRACTED", "source_file": "src/gui/gui_manager_frame.cpp", "source_location": "L3", "weight": 1.0}, {"source": "src_gui_gui_manager_frame_cpp", "target": "gl_setup", "relation": "imports", "confidence": "EXTRACTED", "source_file": "src/gui/gui_manager_frame.cpp", "source_location": "L4", "weight": 1.0}, {"source": "src_gui_gui_manager_frame_cpp", "target": "imgui", "relation": "imports", "confidence": "EXTRACTED", "source_file": "src/gui/gui_manager_frame.cpp", "source_location": "L5", "weight": 1.0}, {"source": "src_gui_gui_manager_frame_cpp", "target": "imgui_impl_opengl3", "relation": "imports", "confidence": "EXTRACTED", "source_file": "src/gui/gui_manager_frame.cpp", "source_location": "L6", "weight": 1.0}, {"source": "src_gui_gui_manager_frame_cpp", "target": "imgui_impl_sdl2", "relation": "imports", "confidence": "EXTRACTED", "source_file": "src/gui/gui_manager_frame.cpp", "source_location": "L7", "weight": 1.0}, {"source": "src_gui_gui_manager_frame_cpp", "target": "sdl", "relation": "imports", "confidence": "EXTRACTED", "source_file": "src/gui/gui_manager_frame.cpp", "source_location": "L8", "weight": 1.0}, {"source": "src_gui_gui_manager_frame_cpp", "target": "gui_manager_frame_run_frame", "relation": "contains", "confidence": "EXTRACTED", "source_file": "src/gui/gui_manager_frame.cpp", "source_location": "L12", "weight": 1.0}, {"source": "src_gui_gui_manager_frame_cpp", "target": "gui_manager_frame_render_master_controls", "relation": "contains", "confidence": "EXTRACTED", "source_file": "src/gui/gui_manager_frame.cpp", "source_location": "L137", "weight": 1.0}, {"source": "gui_manager_frame_run_frame", "target": "gui_manager_frame_render_master_controls", "relation": "calls", "confidence": "EXTRACTED", "source_file": "src/gui/gui_manager_frame.cpp", "source_location": "L78", "weight": 1.0}]}